oblb
oblb/__init__
