Metadata-Version: 1.0
Name: oblb
Version: 0.0.1
Summary: One Banana Load Balancing
Home-page: https://github.com/wnyc/oblb
Author: Adam DePrince
Author-email: adeprince@nypublicradio.org
License: GPL
Platform: UNKNOWN
